deribitsimplebot/__init__.py
deribitsimplebot/bot.py
deribitsimplebot/db.py
deribitsimplebot/exceptions.py
deribitsimplebot/interface.py
deribitsimplebot/order.py
deribitsimplebot-0.2.3.dist-info/WHEEL
deribitsimplebot-0.2.3.dist-info/METADATA
deribitsimplebot-0.2.3.dist-info/RECORD
